{
    "configurations": [
        {
            "name": "Mac",
            "browse": {
                "path": [
                    "${workspaceFolder}"
                ],
                "limitSymbolsToIncludedHeaders": true
            },
            "includePath": [
                "/usr/include",
                "/usr/local/include",
                "/Library/Developer/CommandLineTools/usr/include/c++/v1",
                "/Library/Developer/CommandLineTools/usr/lib/clang/10.0.0/include",
                "/Library/Developer/CommandLineTools/usr/include",
                "/System/Library/Frameworks",
                "/Library/Frameworks",
                "${workspaceFolder}/**"
            ],
            "defines": [],
            "macFrameworkPath": [
                "/System/Library/Frameworks",
                "/Library/Frameworks"
            ],
            "compilerPath": "/usr/bin/clang",
            "cStandard": "c11",
            "cppStandard": "c++17",
            "intelliSenseMode": "clang-x64"
        }
    ],
    "version": 4
}